Metadata-Version: 2.1
Name: PyLaTeX
Version: 1.4.2
Summary: A Python library for creating LaTeX files and snippets
Home-page: https://github.com/JelteF/PyLaTeX
Author: Jelte Fennema
Author-email: pylatex@jeltef.nl
License: MIT
Classifier: Development Status :: 5 - Production/Stable
Classifier: Environment :: Console
Classifier: Intended Audience :: Developers
Classifier: Intended Audience :: Education
Classifier: Intended Audience :: End Users/Desktop
Classifier: Intended Audience :: Science/Research
Classifier: License :: OSI Approved :: MIT License
Classifier: Operating System :: POSIX :: Linux
Classifier: Programming Language :: Python
Classifier: Programming Language :: Python :: 2
Classifier: Programming Language :: Python :: 2.7
Classifier: Programming Language :: Python :: 3
Classifier: Programming Language :: Python :: 3.3
Classifier: Programming Language :: Python :: 3.4
Classifier: Programming Language :: Python :: 3.5
Classifier: Topic :: Software Development :: Code Generators
Classifier: Topic :: Text Processing :: Markup :: LaTeX
Provides-Extra: docs
Provides-Extra: matrices
Provides-Extra: matplotlib
Provides-Extra: quantities
Provides-Extra: testing
Provides-Extra: packaging
Provides-Extra: all
License-File: LICENSE
